{
  "track": {
    "straights": [
      {
        "x_start": [
          0
        ],
        "x_end": [
          0
        ],
        "y_start": [
          0
        ],
        "y_end": [
          2.6457527396898635
        ],
        "x_dir": [
          0
        ],
        "y_dir": [
          1
        ],
        "sector_ind": [
          1
        ]
      },
      {
        "x_start": [
          0.9999999999999999
        ],
        "x_end": [
          4.037709098232539
        ],
        "y_start": [
          3.6457527396898635
        ],
        "y_end": [
          3.6457527396898635
        ],
        "x_dir": [
          1
        ],
        "y_dir": [
          6.123233995736766e-17
        ],
        "sector_ind": [
          3
        ]
      },
      {
        "x_start": [
          5.037709098232538
        ],
        "x_end": [
          5.037709098232538
        ],
        "y_start": [
          4.645752739689863
        ],
        "y_end": [
          4.786796770879198
        ],
        "x_dir": [
          0
        ],
        "y_dir": [
          1
        ],
        "sector_ind": [
          5
        ]
      },
      {
        "x_start": [
          5.33060231704599
        ],
        "x_end": [
          5.418729219941286
        ],
        "y_start": [
          5.4939035520657455
        ],
        "y_end": [
          5.582030454961042
        ],
        "x_dir": [
          0.7071067811865475
        ],
        "y_dir": [
          0.7071067811865476
        ],
        "sector_ind": [
          7
        ]
      },
      {
        "x_start": [
          5.4187292199412855
        ],
        "x_end": [
          5.266103051769351
        ],
        "y_start": [
          6.996244017334137
        ],
        "y_end": [
          7.1488701855060715
        ],
        "x_dir": [
          -0.7071067811865476
        ],
        "y_dir": [
          0.7071067811865475
        ],
        "sector_ind": [
          9
        ]
      },
      {
        "x_start": [
          4.973209832955899
        ],
        "x_end": [
          4.973209832955899
        ],
        "y_start": [
          7.855976966692619
        ],
        "y_end": [
          9.08396477217344
        ],
        "x_dir": [
          -2.220446049250313e-16
        ],
        "y_dir": [
          1
        ],
        "sector_ind": [
          11
        ]
      },
      {
        "x_start": [
          2.9732098329558987
        ],
        "x_end": [
          2.9732098329558987
        ],
        "y_start": [
          9.08396477217344
        ],
        "y_end": [
          6.981295661654662
        ],
        "x_dir": [
          9.957992501029599e-17
        ],
        "y_dir": [
          -1
        ],
        "sector_ind": [
          13
        ]
      },
      {
        "x_start": [
          1.9732098329558987
        ],
        "x_end": [
          0.9999999999999964
        ],
        "y_start": [
          5.981295661654662
        ],
        "y_end": [
          5.981295661654662
        ],
        "x_dir": [
          -1
        ],
        "y_dir": [
          -1.6081226496766364e-16
        ],
        "sector_ind": [
          15
        ]
      },
      {
        "x_start": [
          -3.774758283725532e-15
        ],
        "x_end": [
          -4.712095548617774e-15
        ],
        "y_start": [
          6.981295661654662
        ],
        "y_end": [
          11.404555229023694
        ],
        "x_dir": [
          -2.220446049250313e-16
        ],
        "y_dir": [
          1
        ],
        "sector_ind": [
          17
        ]
      },
      {
        "x_start": [
          1.9999999999999953
        ],
        "x_end": [
          2.0000000000000004
        ],
        "y_start": [
          11.404555229023694
        ],
        "y_end": [
          -2.572899803760884
        ],
        "x_dir": [
          3.4450928483976665e-16
        ],
        "y_dir": [
          -1
        ],
        "sector_ind": [
          19
        ]
      },
      {
        "x_start": [
          4.440892098500626e-16
        ],
        "x_end": [
          -7.025552420450629e-16
        ],
        "y_start": [
          -2.572899803760885
        ],
        "y_end": [
          3.2335245592207684e-15
        ],
        "x_dir": [
          -4.66973964754502e-16
        ],
        "y_dir": [
          1
        ],
        "sector_ind": [
          21
        ]
      }
    ],
    "curves": [
      {
        "c_x": [
          1
        ],
        "c_y": [
          2.6457527396898635
        ],
        "ang_start": [
          3.141592653589793
        ],
        "ang_end": [
          1.5707963267948966
        ]
      },
      {
        "c_x": [
          4.037709098232539
        ],
        "c_y": [
          4.645752739689863
        ],
        "ang_start": [
          -1.5707963267948966
        ],
        "ang_end": [
          0
        ]
      },
      {
        "c_x": [
          6.037709098232538
        ],
        "c_y": [
          4.786796770879198
        ],
        "ang_start": [
          3.141592653589793
        ],
        "ang_end": [
          2.356194490192345
        ]
      },
      {
        "c_x": [
          4.7116224387547385
        ],
        "c_y": [
          6.289137236147589
        ],
        "ang_start": [
          -0.7853981633974477
        ],
        "ang_end": [
          0.7853981633974488
        ]
      },
      {
        "c_x": [
          5.973209832955899
        ],
        "c_y": [
          7.855976966692619
        ],
        "ang_start": [
          -2.356194490192345
        ],
        "ang_end": [
          -3.141592653589793
        ]
      },
      {
        "c_x": [
          3.9732098329558987
        ],
        "c_y": [
          9.08396477217344
        ],
        "ang_start": [
          0
        ],
        "ang_end": [
          3.141592653589793
        ]
      },
      {
        "c_x": [
          1.9732098329558987
        ],
        "c_y": [
          6.981295661654662
        ],
        "ang_start": [
          0
        ],
        "ang_end": [
          -1.5707963267948966
        ]
      },
      {
        "c_x": [
          0.9999999999999962
        ],
        "c_y": [
          6.981295661654662
        ],
        "ang_start": [
          -1.5707963267948963
        ],
        "ang_end": [
          -3.141592653589793
        ]
      },
      {
        "c_x": [
          0.9999999999999953
        ],
        "c_y": [
          11.404555229023694
        ],
        "ang_start": [
          3.141592653589793
        ],
        "ang_end": [
          0
        ]
      },
      {
        "c_x": [
          1.0000000000000004
        ],
        "c_y": [
          -2.5728998037608846
        ],
        "ang_start": [
          4.440892098500626e-16
        ],
        "ang_end": [
          -3.1415926535897927
        ]
      }
    ]
  },
  "powerSettings": [
    {
      "length": 45.35576125182623,
      "powerSetting": 229.5401159042506
    },
    {
      "length": 45.35576125182623,
      "powerSetting": 252.25514359268732
    },
    {
      "length": 45.35576125182623,
      "powerSetting": 247.61603372728814
    },
    {
      "length": 45.35576125182623,
      "powerSetting": 229.33610653765234
    },
    {
      "length": 45.35576125182623,
      "powerSetting": 237.06194986405416
    },
    {
      "length": 45.35576125182623,
      "powerSetting": 223.7938757369438
    },
    {
      "length": 45.35576125182623,
      "powerSetting": 180.88506407432135
    },
    {
      "length": 188.49555921538757,
      "powerSetting": 251.51521158925223
    },
    {
      "length": 52.07501311255781,
      "powerSetting": 138.79752999587652
    },
    {
      "length": 52.07501311255781,
      "powerSetting": 193.65736537448845
    },
    {
      "length": 52.07501311255781,
      "powerSetting": 242.97204805811097
    },
    {
      "length": 52.07501311255781,
      "powerSetting": 4.496822567904613
    },
    {
      "length": 52.07501311255781,
      "powerSetting": 238.93239736344762
    },
    {
      "length": 52.07501311255781,
      "powerSetting": 118.80929685729278
    },
    {
      "length": 52.07501311255781,
      "powerSetting": 88.40120264533036
    },
    {
      "length": 188.49555921538752,
      "powerSetting": 240.8974842104278
    },
    {
      "length": 2.8208806237866924,
      "powerSetting": 251.3363581556757
    },
    {
      "length": 2.8208806237866924,
      "powerSetting": 254.82319757337459
    },
    {
      "length": 2.8208806237866924,
      "powerSetting": 253.79194577998678
    },
    {
      "length": 2.8208806237866924,
      "powerSetting": 234.04740477155295
    },
    {
      "length": 2.8208806237866924,
      "powerSetting": 253.05340079140927
    },
    {
      "length": 2.8208806237866924,
      "powerSetting": 232.46668551854467
    },
    {
      "length": 94.24777960769379,
      "powerSetting": 244.39526405486103
    },
    {
      "length": 2.492605225689294,
      "powerSetting": 253.0895175192805
    },
    {
      "length": 2.492605225689294,
      "powerSetting": 230.8098796323012
    },
    {
      "length": 2.492605225689294,
      "powerSetting": 253.84096756014506
    },
    {
      "length": 2.492605225689294,
      "powerSetting": 251.90097326681402
    },
    {
      "length": 2.492605225689294,
      "powerSetting": 217.3080505780555
    },
    {
      "length": 2.492605225689294,
      "powerSetting": 184.7575866310363
    },
    {
      "length": 188.49555921538757,
      "powerSetting": 237.53382371794828
    },
    {
      "length": 4.3169199400357385,
      "powerSetting": 239.67418337901213
    },
    {
      "length": 4.3169199400357385,
      "powerSetting": 242.78697291460045
    },
    {
      "length": 4.3169199400357385,
      "powerSetting": 243.46060156176898
    },
    {
      "length": 4.3169199400357385,
      "powerSetting": 238.7190206617917
    },
    {
      "length": 4.3169199400357385,
      "powerSetting": 254.22742094974862
    },
    {
      "length": 4.3169199400357385,
      "powerSetting": 254.79076123074236
    },
    {
      "length": 94.24777960769383,
      "powerSetting": 244.46284548838344
    },
    {
      "length": 24.55975610961641,
      "powerSetting": 253.4124497627629
    },
    {
      "length": 24.55975610961641,
      "powerSetting": 243.26542993462698
    },
    {
      "length": 24.55975610961641,
      "powerSetting": 243.32569985619674
    },
    {
      "length": 24.55975610961641,
      "powerSetting": 220.41094479868056
    },
    {
      "length": 24.55975610961641,
      "powerSetting": 230.75525883026776
    },
    {
      "length": 24.55975610961641,
      "powerSetting": 151.63730262567265
    },
    {
      "length": 376.99111843077515,
      "powerSetting": 244.52063419481536
    },
    {
      "length": 42.05338221037555,
      "powerSetting": 159.15304059217445
    },
    {
      "length": 42.05338221037555,
      "powerSetting": 194.91035531228903
    },
    {
      "length": 42.05338221037555,
      "powerSetting": 178.77942326655332
    },
    {
      "length": 42.05338221037555,
      "powerSetting": 166.6346212632447
    },
    {
      "length": 42.05338221037555,
      "powerSetting": 206.21909490846224
    },
    {
      "length": 42.05338221037555,
      "powerSetting": 157.63563886816272
    },
    {
      "length": 188.49555921538757,
      "powerSetting": 242.2828320951035
    },
    {
      "length": 19.464196659118045,
      "powerSetting": 247.14862974283815
    },
    {
      "length": 19.464196659118045,
      "powerSetting": 198.33821146228198
    },
    {
      "length": 19.464196659118045,
      "powerSetting": 216.2717718355791
    },
    {
      "length": 19.464196659118045,
      "powerSetting": 150.84088595616538
    },
    {
      "length": 19.464196659118045,
      "powerSetting": 240.8972811298661
    },
    {
      "length": 19.464196659118045,
      "powerSetting": 98.12424969732346
    },
    {
      "length": 188.4955592153876,
      "powerSetting": 214.27351096115189
    },
    {
      "length": 75.82730686918342,
      "powerSetting": 231.00201147449195
    },
    {
      "length": 75.82730686918342,
      "powerSetting": 221.33652728572577
    },
    {
      "length": 75.82730686918342,
      "powerSetting": 230.91260921519455
    },
    {
      "length": 75.82730686918342,
      "powerSetting": 188.7341673965778
    },
    {
      "length": 75.82730686918342,
      "powerSetting": 72.93574528244436
    },
    {
      "length": 75.82730686918342,
      "powerSetting": 24.3579436678563
    },
    {
      "length": 75.82730686918342,
      "powerSetting": 71.91381299655485
    },
    {
      "length": 376.99111843077515,
      "powerSetting": 252.0744601344005
    },
    {
      "length": 239.61351484773564,
      "powerSetting": 252.13445620330398
    },
    {
      "length": 239.61351484773564,
      "powerSetting": 254.9953233355421
    },
    {
      "length": 239.61351484773564,
      "powerSetting": 254.5339585495784
    },
    {
      "length": 239.61351484773564,
      "powerSetting": 254.61356354711822
    },
    {
      "length": 239.61351484773564,
      "powerSetting": 253.15396481459499
    },
    {
      "length": 239.61351484773564,
      "powerSetting": 253.9048578291656
    },
    {
      "length": 239.61351484773564,
      "powerSetting": 250.14836205759195
    },
    {
      "length": 376.99111843077515,
      "powerSetting": 253.57324026485398
    },
    {
      "length": 51.457996075217764,
      "powerSetting": 248.60062099901012
    },
    {
      "length": 51.457996075217764,
      "powerSetting": 252.80486119353293
    },
    {
      "length": 51.457996075217764,
      "powerSetting": 254.91941560126332
    },
    {
      "length": 51.457996075217764,
      "powerSetting": 254.9696385731503
    },
    {
      "length": 51.457996075217764,
      "powerSetting": 254.59020868283662
    },
    {
      "length": 51.457996075217764,
      "powerSetting": 251.2818558692955
    }
  ]
}